ingestkit/__init__.py
ingestkit/cli.py
ingestkit-0.1.9.dist-info/METADATA
ingestkit-0.1.9.dist-info/WHEEL
ingestkit-0.1.9.dist-info/entry_points.txt
ingestkit-0.1.9.dist-info/top_level.txt
ingestkit-0.1.9.dist-info/RECORD
